tricco/__init__.py
tricco/compute.py
tricco/cubulation_functions.py
tricco/grid_functions.py
tricco/prepare.py
tricco/alternatives/__init__.py
tricco/alternatives/nwx.py
tricco/alternatives/ownbfs.py
tricco-1.1.0.dist-info/LICENSE
tricco-1.1.0.dist-info/METADATA
tricco-1.1.0.dist-info/WHEEL
tricco-1.1.0.dist-info/top_level.txt
tricco-1.1.0.dist-info/RECORD
